{
  "generated": "2026-07-22",
  "apod": {
    "title": "The Corona Australis Molecular Cloud and the Chandelier Cluster",
    "date": "2026-07-22",
    "explanation": "The Southern Crown (Corona Australis) dazzles with young and ancient celestial jewels. The Corona Australis Cloud is a collage of reflection and emission nebulae on the left of today\u2019s image. At 430 light years away, this cloud is one of the closest star-forming regions to Earth. It contains gas cool enough (-260 Celsius or -440 Fahrenheit) to collapse into protostars. Recently formed stars paint blue hues across the cloud as their light reflects off surrounding material. The waltz of the R Coronae Australis binary system stirs up the nebula NGC 6729. The younger of the pair ionizes nearby gas with its ultraviolet light, causing it to glow. The Chandelier Cluster (NGC 6723) dangles from the top right, but is actually tens of thousands of light years farther away than its apparent star-forming neighbor. While NGC 6723 experienced multiple periods of star formation creating slightly younger stars, the chandelier twinkles with stars almost as old as the universe.",
    "media_type": "image",
    "url": "https://apod.nasa.gov/apod/image/2607/corona_australis_1024.jpg",
    "hdurl": "https://apod.nasa.gov/apod/image/2607/corona_australis.jpg"
  },
  "events": {
    "events": [
      {
        "id": "us7000t2dz",
        "title": "M5.0 Earthquake - 55 km WSW of Langsa, Indonesia",
        "category": "Earthquake",
        "date": "2026-07-22T04:18:22.071000Z",
        "coordinates": [
          97.5238,
          4.2441
        ]
      },
      {
        "id": "us7000t2a7",
        "title": "M5.1 Earthquake - 7 km WNW of Kalbay, Philippines",
        "category": "Earthquake",
        "date": "2026-07-21T18:33:27.762000Z",
        "coordinates": [
          125.4295,
          5.739
        ]
      },
      {
        "id": "us7000t26b",
        "title": "M5.3 Earthquake - 132 km ENE of Santa Cruz das Flores, Portugal",
        "category": "Earthquake",
        "date": "2026-07-21T13:13:11.261000Z",
        "coordinates": [
          -29.7175,
          39.9371
        ]
      },
      {
        "id": "us7000t25y",
        "title": "M5.6 Earthquake - Kermadec Islands region",
        "category": "Earthquake",
        "date": "2026-07-21T12:14:33.338000Z",
        "coordinates": [
          -176.9951,
          -29.5116
        ]
      },
      {
        "id": "us7000t25j",
        "title": "M5.0 Earthquake - 58 km SSW of Merizo Village, Guam",
        "category": "Earthquake",
        "date": "2026-07-21T11:09:45.478000Z",
        "coordinates": [
          144.3814,
          12.8216
        ]
      },
      {
        "id": "us7000t23v",
        "title": "M5.0 Earthquake - Mid-Indian Ridge",
        "category": "Earthquake",
        "date": "2026-07-21T03:17:09.781000Z",
        "coordinates": [
          73.8261,
          -27.6011
        ]
      },
      {
        "id": "us7000t23e",
        "title": "M5.2 Earthquake - northern Mid-Atlantic Ridge",
        "category": "Earthquake",
        "date": "2026-07-21T01:03:34.930000Z",
        "coordinates": [
          -45.0893,
          25.9041
        ]
      },
      {
        "id": "us7000t232",
        "title": "M5.0 Earthquake - 141 km SSW of Gataivai, Samoa",
        "category": "Earthquake",
        "date": "2026-07-20T23:37:57.854000Z",
        "coordinates": [
          -172.8619,
          -14.9677
        ]
      },
      {
        "id": "us7000t21z",
        "title": "M5.6 Earthquake - northern Mid-Atlantic Ridge",
        "category": "Earthquake",
        "date": "2026-07-20T21:28:30.326000Z",
        "coordinates": [
          -45.1002,
          14.5216
        ]
      },
      {
        "id": "us7000t21e",
        "title": "M5.0 Earthquake - south of the Kermadec Islands",
        "category": "Earthquake",
        "date": "2026-07-20T20:44:19.902000Z",
        "coordinates": [
          -178.0878,
          -32.759
        ]
      },
      {
        "id": "us7000t1wn",
        "title": "M5.2 Earthquake - 22 km NNW of Scarborough, Trinidad and Tobago",
        "category": "Earthquake",
        "date": "2026-07-20T09:45:10.282000Z",
        "coordinates": [
          -60.8041,
          11.3742
        ]
      },
      {
        "id": "us7000t1wm",
        "title": "M5.1 Earthquake - 83 km W of Tobelo, Indonesia",
        "category": "Earthquake",
        "date": "2026-07-20T09:40:43.255000Z",
        "coordinates": [
          127.2659,
          1.6021
        ]
      },
      {
        "id": "us7000t1w2",
        "title": "M5.6 Earthquake - 208 km SW of Port McNeill, Canada",
        "category": "Earthquake",
        "date": "2026-07-20T06:41:30.614000Z",
        "coordinates": [
          -129.342,
          49.4076
        ]
      },
      {
        "id": "us7000t213",
        "title": "M5.5 Earthquake - Pacific-Antarctic Ridge",
        "category": "Earthquake",
        "date": "2026-07-20T05:38:56.465000Z",
        "coordinates": [
          -141.7631,
          -57.2663
        ]
      },
      {
        "id": "us7000t1vq",
        "title": "M5.2 Earthquake - 27 km S of Jav\u0101nr\u016bd, Iran",
        "category": "Earthquake",
        "date": "2026-07-20T03:48:50.791000Z",
        "coordinates": [
          46.5578,
          34.5521
        ]
      }
    ]
  },
  "asteroids": {
    "asteroids": [
      {
        "name": "(2015 EG7)",
        "hazardous": false,
        "diameter_m": 20,
        "close_approach_date": "2026-07-22",
        "miss_distance_km": 20140894,
        "velocity_kmh": 60637
      },
      {
        "name": "(2007 SW2)",
        "hazardous": false,
        "diameter_m": 303,
        "close_approach_date": "2026-07-22",
        "miss_distance_km": 35390107,
        "velocity_kmh": 36791
      },
      {
        "name": "523728 (2014 ON344)",
        "hazardous": false,
        "diameter_m": 179,
        "close_approach_date": "2026-07-22",
        "miss_distance_km": 52949732,
        "velocity_kmh": 49300
      },
      {
        "name": "(2015 TO237)",
        "hazardous": false,
        "diameter_m": 1067,
        "close_approach_date": "2026-07-22",
        "miss_distance_km": 65196291,
        "velocity_kmh": 88223
      },
      {
        "name": "(2015 VC105)",
        "hazardous": false,
        "diameter_m": 54,
        "close_approach_date": "2026-07-22",
        "miss_distance_km": 73020003,
        "velocity_kmh": 17795
      },
      {
        "name": "(2019 BN2)",
        "hazardous": false,
        "diameter_m": 29,
        "close_approach_date": "2026-07-23",
        "miss_distance_km": 18101269,
        "velocity_kmh": 41905
      },
      {
        "name": "(2014 GJ1)",
        "hazardous": false,
        "diameter_m": 86,
        "close_approach_date": "2026-07-23",
        "miss_distance_km": 18262849,
        "velocity_kmh": 18944
      },
      {
        "name": "253062 (2002 TC70)",
        "hazardous": false,
        "diameter_m": 358,
        "close_approach_date": "2026-07-23",
        "miss_distance_km": 20041502,
        "velocity_kmh": 10208
      },
      {
        "name": "(2023 OV)",
        "hazardous": false,
        "diameter_m": 1107,
        "close_approach_date": "2026-07-23",
        "miss_distance_km": 35785875,
        "velocity_kmh": 62586
      },
      {
        "name": "(2017 FZ2)",
        "hazardous": false,
        "diameter_m": 28,
        "close_approach_date": "2026-07-23",
        "miss_distance_km": 40553314,
        "velocity_kmh": 33689
      }
    ]
  },
  "weather": {
    "city": "City of Zagreb",
    "temp_c": 19.2,
    "feels_c": 19.1,
    "humidity": 70,
    "condition": "Clouds",
    "description": "scattered clouds",
    "icon": "03d",
    "wind_kmh": 5.4
  },
  "forecast_today": {
    "date": "2026-07-22",
    "city": "City of Zagreb",
    "temp_min_c": 17.6,
    "temp_max_c": 25.7,
    "humidity": 52,
    "condition": "Clouds",
    "description": "clouds",
    "icon": "03d",
    "wind_kmh": 6.6,
    "samples": 7
  },
  "forecast": {
    "date": "2026-07-23",
    "city": "City of Zagreb",
    "temp_min_c": 14.8,
    "temp_max_c": 27.4,
    "humidity": 64,
    "condition": "Rain",
    "description": "light rain",
    "icon": "10d",
    "wind_kmh": 5.2
  },
  "forecast_day_after": {
    "date": "2026-07-24",
    "city": "City of Zagreb",
    "temp_min_c": 12.3,
    "temp_max_c": 26.0,
    "humidity": 56,
    "condition": "Clear",
    "description": "clear sky",
    "icon": "01d",
    "wind_kmh": 6.8
  },
  "uv": {
    "uv": 1.5,
    "band": "low",
    "daily_max": 6.6,
    "peak_time": "2026-07-22T13:00",
    "safe_minutes": 111,
    "skin_type": 2,
    "hourly": [
      {
        "time": "2026-07-22T00:00",
        "uv": 0.0
      },
      {
        "time": "2026-07-22T01:00",
        "uv": 0.0
      },
      {
        "time": "2026-07-22T02:00",
        "uv": 0.0
      },
      {
        "time": "2026-07-22T03:00",
        "uv": 0.0
      },
      {
        "time": "2026-07-22T04:00",
        "uv": 0.0
      },
      {
        "time": "2026-07-22T05:00",
        "uv": 0.0
      },
      {
        "time": "2026-07-22T06:00",
        "uv": 0.1
      },
      {
        "time": "2026-07-22T07:00",
        "uv": 0.5
      },
      {
        "time": "2026-07-22T08:00",
        "uv": 1.4
      },
      {
        "time": "2026-07-22T09:00",
        "uv": 2.6
      },
      {
        "time": "2026-07-22T10:00",
        "uv": 4.0
      },
      {
        "time": "2026-07-22T11:00",
        "uv": 5.3
      },
      {
        "time": "2026-07-22T12:00",
        "uv": 6.2
      },
      {
        "time": "2026-07-22T13:00",
        "uv": 6.6
      },
      {
        "time": "2026-07-22T14:00",
        "uv": 3.1
      },
      {
        "time": "2026-07-22T15:00",
        "uv": 4.0
      },
      {
        "time": "2026-07-22T16:00",
        "uv": 2.1
      },
      {
        "time": "2026-07-22T17:00",
        "uv": 4.2
      },
      {
        "time": "2026-07-22T18:00",
        "uv": 2.8
      },
      {
        "time": "2026-07-22T19:00",
        "uv": 1.4
      },
      {
        "time": "2026-07-22T20:00",
        "uv": 0.5
      },
      {
        "time": "2026-07-22T21:00",
        "uv": 0.1
      },
      {
        "time": "2026-07-22T22:00",
        "uv": 0.0
      },
      {
        "time": "2026-07-22T23:00",
        "uv": 0.0
      }
    ],
    "fetched_at": "2026-07-22T07:47:10+02:00"
  }
}