{
  "generated": "2026-04-18",
  "apod": {
    "error": "HTTPSConnectionPool(host='api.nasa.gov', port=443): Read timed out. (read timeout=10)"
  },
  "events": {
    "error": "503 Server Error: Service Unavailable for url: https://api.nasa.gov/EONET/v3/events?status=open&limit=20&api_key=yfd7roIVefAGFw0bhPilw6Wnby8oweeCEga8asPl"
  },
  "asteroids": {
    "asteroids": [
      {
        "name": "(2026 HQ)",
        "hazardous": false,
        "diameter_m": 4,
        "close_approach_date": "2026-04-18",
        "miss_distance_km": 165015,
        "velocity_kmh": 13395
      },
      {
        "name": "(2026 GM1)",
        "hazardous": false,
        "diameter_m": 48,
        "close_approach_date": "2026-04-18",
        "miss_distance_km": 1329731,
        "velocity_kmh": 20262
      },
      {
        "name": "(2026 GR2)",
        "hazardous": false,
        "diameter_m": 20,
        "close_approach_date": "2026-04-18",
        "miss_distance_km": 2946052,
        "velocity_kmh": 23545
      },
      {
        "name": "(2026 FJ6)",
        "hazardous": false,
        "diameter_m": 150,
        "close_approach_date": "2026-04-18",
        "miss_distance_km": 6039750,
        "velocity_kmh": 35443
      },
      {
        "name": "(2026 GF1)",
        "hazardous": false,
        "diameter_m": 43,
        "close_approach_date": "2026-04-18",
        "miss_distance_km": 8140575,
        "velocity_kmh": 15478
      },
      {
        "name": "(2015 KJ122)",
        "hazardous": true,
        "diameter_m": 237,
        "close_approach_date": "2026-04-18",
        "miss_distance_km": 8649242,
        "velocity_kmh": 73527
      },
      {
        "name": "(2024 TX13)",
        "hazardous": false,
        "diameter_m": 73,
        "close_approach_date": "2026-04-18",
        "miss_distance_km": 16870739,
        "velocity_kmh": 16059
      },
      {
        "name": "(2021 VE4)",
        "hazardous": false,
        "diameter_m": 94,
        "close_approach_date": "2026-04-18",
        "miss_distance_km": 23602447,
        "velocity_kmh": 43982
      },
      {
        "name": "(2026 FU4)",
        "hazardous": false,
        "diameter_m": 41,
        "close_approach_date": "2026-04-18",
        "miss_distance_km": 24324567,
        "velocity_kmh": 9975
      },
      {
        "name": "(2023 QD)",
        "hazardous": false,
        "diameter_m": 27,
        "close_approach_date": "2026-04-18",
        "miss_distance_km": 27118453,
        "velocity_kmh": 38072
      }
    ]
  },
  "weather": {
    "city": "Zagreb",
    "temp_c": 11.5,
    "feels_c": 10.5,
    "humidity": 68,
    "condition": "Clouds",
    "description": "broken clouds",
    "icon": "04n",
    "wind_kmh": 0.9
  },
  "forecast": {
    "date": "2026-04-19",
    "city": "City of Zagreb",
    "temp_min_c": 7.7,
    "temp_max_c": 21.5,
    "humidity": 62,
    "condition": "Clouds",
    "description": "broken clouds",
    "icon": "04d",
    "wind_kmh": 5.6
  }
}